chora/__init__.py
chora/__main__.py
chora/cli.py
chora/handler.py
chora/py.typed
chora/server.py
chora-0.3.0.dist-info/licenses/LICENSE
chora-0.3.0.dist-info/METADATA
chora-0.3.0.dist-info/WHEEL
chora-0.3.0.dist-info/entry_points.txt
chora-0.3.0.dist-info/top_level.txt
chora-0.3.0.dist-info/RECORD
